{"metrics": [{"reward_score": 8, "metric_time": 19354, "start_time": 18008, "elapsed_time_in_milliseconds": 1346, "episode": 1, "trial": 1, "phase": "training", "completion_percentage": 6, "episode_status": "Off track"}, {"reward_score": 19, "metric_time": 21419, "start_time": 19410, "elapsed_time_in_milliseconds": 2009, "episode": 2, "trial": 2, "phase": "training", "completion_percentage": 10, "episode_status": "Off track"}, {"reward_score": 9, "metric_time": 23085, "start_time": 21478, "elapsed_time_in_milliseconds": 1607, "episode": 3, "trial": 3, "phase": "training", "completion_percentage": 8, "episode_status": "Off track"}, {"reward_score": 12, "metric_time": 24685, "start_time": 23147, "elapsed_time_in_milliseconds": 1538, "episode": 4, "trial": 4, "phase": "training", "completion_percentage": 5, "episode_status": "Off track"}, {"reward_score": 17, "metric_time": 26748, "start_time": 24733, "elapsed_time_in_milliseconds": 2015, "episode": 5, "trial": 5, "phase": "training", "completion_percentage": 9, "episode_status": "Off track"}, {"reward_score": 8, "metric_time": 28083, "start_time": 26814, "elapsed_time_in_milliseconds": 1269, "episode": 6, "trial": 6, "phase": "training", "completion_percentage": 4, "episode_status": "Off track"}, {"reward_score": 11, "metric_time": 29551, "start_time": 28143, "elapsed_time_in_milliseconds": 1408, "episode": 7, "trial": 7, "phase": "training", "completion_percentage": 4, "episode_status": "Off track"}, {"reward_score": 18, "metric_time": 32552, "start_time": 29618, "elapsed_time_in_milliseconds": 2934, "episode": 8, "trial": 8, "phase": "training", "completion_percentage": 16, "episode_status": "Off track"}, {"reward_score": 13, "metric_time": 34348, "start_time": 32615, "elapsed_time_in_milliseconds": 1733, "episode": 9, "trial": 9, "phase": "training", "completion_percentage": 7, "episode_status": "Off track"}, {"reward_score": 8, "metric_time": 35684, "start_time": 34417, "elapsed_time_in_milliseconds": 1267, "episode": 10, "trial": 10, "phase": "training", "completion_percentage": 5, "episode_status": "Off track"}, {"reward_score": 7, "metric_time": 37013, "start_time": 35747, "elapsed_time_in_milliseconds": 1266, "episode": 11, "trial": 11, "phase": "training", "completion_percentage": 5, "episode_status": "Off track"}, {"reward_score": 13, "metric_time": 39748, "start_time": 37084, "elapsed_time_in_milliseconds": 2664, "episode": 12, "trial": 12, "phase": "training", "completion_percentage": 13, "episode_status": "Off track"}, {"reward_score": 21, "metric_time": 42018, "start_time": 39814, "elapsed_time_in_milliseconds": 2204, "episode": 13, "trial": 13, "phase": "training", "completion_percentage": 10, "episode_status": "Off track"}, {"reward_score": 10, "metric_time": 43476, "start_time": 42084, "elapsed_time_in_milliseconds": 1392, "episode": 14, "trial": 14, "phase": "training", "completion_percentage": 5, "episode_status": "Off track"}, {"reward_score": 6, "metric_time": 44687, "start_time": 43544, "elapsed_time_in_milliseconds": 1143, "episode": 15, "trial": 15, "phase": "training", "completion_percentage": 3, "episode_status": "Off track"}, {"reward_score": 19, "metric_time": 47547, "start_time": 44751, "elapsed_time_in_milliseconds": 2796, "episode": 16, "trial": 16, "phase": "training", "completion_percentage": 15, "episode_status": "Off track"}, {"reward_score": 14, "metric_time": 49290, "start_time": 47608, "elapsed_time_in_milliseconds": 1682, "episode": 17, "trial": 17, "phase": "training", "completion_percentage": 7, "episode_status": "Off track"}, {"reward_score": 20, "metric_time": 52684, "start_time": 49348, "elapsed_time_in_milliseconds": 3336, "episode": 18, "trial": 18, "phase": "training", "completion_percentage": 20, "episode_status": "Off track"}, {"reward_score": 7, "metric_time": 53818, "start_time": 52750, "elapsed_time_in_milliseconds": 1068, "episode": 19, "trial": 19, "phase": "training", "completion_percentage": 3, "episode_status": "Off track"}, {"reward_score": 14, "metric_time": 57815, "start_time": 53881, "elapsed_time_in_milliseconds": 3934, "episode": 20, "trial": 20, "phase": "training", "completion_percentage": 23, "episode_status": "Off track"}, {"reward_score": 11, "metric_time": 59252, "start_time": 57941, "elapsed_time_in_milliseconds": 1311, "episode": 20, "trial": 20, "phase": "evaluation", "completion_percentage": 4, "episode_status": "Off track"}, {"reward_score": 20, "metric_time": 66609, "start_time": 59348, "elapsed_time_in_milliseconds": 7261, "episode": 20, "trial": 20, "phase": "evaluation", "completion_percentage": 45, "episode_status": "Off track"}, {"reward_score": 17, "metric_time": 68682, "start_time": 66681, "elapsed_time_in_milliseconds": 2001, "episode": 20, "trial": 20, "phase": "evaluation", "completion_percentage": 10, "episode_status": "Off track"}, {"reward_score": 25, "metric_time": 77091, "start_time": 68751, "elapsed_time_in_milliseconds": 8340, "episode": 20, "trial": 20, "phase": "evaluation", "completion_percentage": 48, "episode_status": "Off track"}, {"reward_score": 32, "metric_time": 85549, "start_time": 77144, "elapsed_time_in_milliseconds": 8405, "episode": 20, "trial": 20, "phase": "evaluation", "completion_percentage": 48, "episode_status": "Off track"}, {"reward_score": 21, "metric_time": 89819, "start_time": 85612, "elapsed_time_in_milliseconds": 4207, "episode": 21, "trial": 1, "phase": "training", "completion_percentage": 22, "episode_status": "Off track"}, {"reward_score": 41, "metric_time": 93419, "start_time": 89881, "elapsed_time_in_milliseconds": 3538, "episode": 22, "trial": 2, "phase": "training", "completion_percentage": 18, "episode_status": "Off track"}, {"reward_score": 13, "metric_time": 95490, "start_time": 93483, "elapsed_time_in_milliseconds": 2007, "episode": 23, "trial": 3, "phase": "training", "completion_percentage": 10, "episode_status": "Off track"}, {"reward_score": 16, "metric_time": 98617, "start_time": 95563, "elapsed_time_in_milliseconds": 3054, "episode": 24, "trial": 4, "phase": "training", "completion_percentage": 18, "episode_status": "Off track"}, {"reward_score": 7, "metric_time": 99956, "start_time": 98675, "elapsed_time_in_milliseconds": 1281, "episode": 25, "trial": 5, "phase": "training", "completion_percentage": 4, "episode_status": "Off track"}, {"reward_score": 10, "metric_time": 101550, "start_time": 100015, "elapsed_time_in_milliseconds": 1535, "episode": 26, "trial": 6, "phase": "training", "completion_percentage": 5, "episode_status": "Off track"}, {"reward_score": 21, "metric_time": 103881, "start_time": 101615, "elapsed_time_in_milliseconds": 2266, "episode": 27, "trial": 7, "phase": "training", "completion_percentage": 12, "episode_status": "Off track"}, {"reward_score": 19, "metric_time": 107150, "start_time": 103929, "elapsed_time_in_milliseconds": 3221, "episode": 28, "trial": 8, "phase": "training", "completion_percentage": 18, "episode_status": "Off track"}, {"reward_score": 11, "metric_time": 108624, "start_time": 107214, "elapsed_time_in_milliseconds": 1410, "episode": 29, "trial": 9, "phase": "training", "completion_percentage": 5, "episode_status": "Off track"}, {"reward_score": 10, "metric_time": 110150, "start_time": 108687, "elapsed_time_in_milliseconds": 1463, "episode": 30, "trial": 10, "phase": "training", "completion_percentage": 6, "episode_status": "Off track"}, {"reward_score": 22, "metric_time": 113750, "start_time": 110209, "elapsed_time_in_milliseconds": 3541, "episode": 31, "trial": 11, "phase": "training", "completion_percentage": 19, "episode_status": "Off track"}, {"reward_score": 9, "metric_time": 115083, "start_time": 113819, "elapsed_time_in_milliseconds": 1264, "episode": 32, "trial": 12, "phase": "training", "completion_percentage": 4, "episode_status": "Off track"}, {"reward_score": 15, "metric_time": 117221, "start_time": 115147, "elapsed_time_in_milliseconds": 2074, "episode": 33, "trial": 13, "phase": "training", "completion_percentage": 9, "episode_status": "Off track"}, {"reward_score": 15, "metric_time": 119150, "start_time": 117286, "elapsed_time_in_milliseconds": 1864, "episode": 34, "trial": 14, "phase": "training", "completion_percentage": 8, "episode_status": "Off track"}, {"reward_score": 7, "metric_time": 120416, "start_time": 119207, "elapsed_time_in_milliseconds": 1209, "episode": 35, "trial": 15, "phase": "training", "completion_percentage": 3, "episode_status": "Off track"}, {"reward_score": 36, "metric_time": 123946, "start_time": 120484, "elapsed_time_in_milliseconds": 3462, "episode": 36, "trial": 16, "phase": "training", "completion_percentage": 19, "episode_status": "Off track"}, {"reward_score": 26, "metric_time": 126888, "start_time": 123983, "elapsed_time_in_milliseconds": 2905, "episode": 37, "trial": 17, "phase": "training", "completion_percentage": 14, "episode_status": "Off track"}, {"reward_score": 10, "metric_time": 128419, "start_time": 126948, "elapsed_time_in_milliseconds": 1471, "episode": 38, "trial": 18, "phase": "training", "completion_percentage": 5, "episode_status": "Off track"}, {"reward_score": 12, "metric_time": 130416, "start_time": 128478, "elapsed_time_in_milliseconds": 1938, "episode": 39, "trial": 19, "phase": "training", "completion_percentage": 10, "episode_status": "Off track"}, {"reward_score": 38, "metric_time": 134221, "start_time": 130476, "elapsed_time_in_milliseconds": 3745, "episode": 40, "trial": 20, "phase": "training", "completion_percentage": 21, "episode_status": "Off track"}, {"reward_score": 46, "metric_time": 138142, "start_time": 134343, "elapsed_time_in_milliseconds": 3799, "episode": 40, "trial": 20, "phase": "evaluation", "completion_percentage": 21, "episode_status": "Off track"}, {"reward_score": 46, "metric_time": 141947, "start_time": 138217, "elapsed_time_in_milliseconds": 3730, "episode": 40, "trial": 20, "phase": "evaluation", "completion_percentage": 21, "episode_status": "Off track"}, {"reward_score": 33, "metric_time": 145026, "start_time": 142012, "elapsed_time_in_milliseconds": 3014, "episode": 40, "trial": 20, "phase": "evaluation", "completion_percentage": 16, "episode_status": "Off track"}, {"reward_score": 44, "metric_time": 148885, "start_time": 145081, "elapsed_time_in_milliseconds": 3804, "episode": 40, "trial": 20, "phase": "evaluation", "completion_percentage": 21, "episode_status": "Off track"}, {"reward_score": 51, "metric_time": 153009, "start_time": 148951, "elapsed_time_in_milliseconds": 4058, "episode": 40, "trial": 20, "phase": "evaluation", "completion_percentage": 22, "episode_status": "Off track"}, {"reward_score": 21, "metric_time": 156473, "start_time": 153078, "elapsed_time_in_milliseconds": 3395, "episode": 41, "trial": 1, "phase": "training", "completion_percentage": 19, "episode_status": "Off track"}, {"reward_score": 30, "metric_time": 159550, "start_time": 156552, "elapsed_time_in_milliseconds": 2998, "episode": 42, "trial": 2, "phase": "training", "completion_percentage": 16, "episode_status": "Off track"}, {"reward_score": 30, "metric_time": 162955, "start_time": 159615, "elapsed_time_in_milliseconds": 3340, "episode": 43, "trial": 3, "phase": "training", "completion_percentage": 17, "episode_status": "Off track"}, {"reward_score": 17, "metric_time": 165215, "start_time": 163015, "elapsed_time_in_milliseconds": 2200, "episode": 44, "trial": 4, "phase": "training", "completion_percentage": 10, "episode_status": "Off track"}, {"reward_score": 11, "metric_time": 166685, "start_time": 165285, "elapsed_time_in_milliseconds": 1400, "episode": 45, "trial": 5, "phase": "training", "completion_percentage": 5, "episode_status": "Off track"}, {"reward_score": 7, "metric_time": 167886, "start_time": 166755, "elapsed_time_in_milliseconds": 1131, "episode": 46, "trial": 6, "phase": "training", "completion_percentage": 3, "episode_status": "Off track"}, {"reward_score": 41, "metric_time": 172546, "start_time": 167945, "elapsed_time_in_milliseconds": 4601, "episode": 47, "trial": 7, "phase": "training", "completion_percentage": 26, "episode_status": "Off track"}, {"reward_score": 28, "metric_time": 175423, "start_time": 172619, "elapsed_time_in_milliseconds": 2804, "episode": 48, "trial": 8, "phase": "training", "completion_percentage": 14, "episode_status": "Off track"}, {"reward_score": 11, "metric_time": 177089, "start_time": 175480, "elapsed_time_in_milliseconds": 1609, "episode": 49, "trial": 9, "phase": "training", "completion_percentage": 6, "episode_status": "Off track"}, {"reward_score": 28, "metric_time": 181081, "start_time": 177151, "elapsed_time_in_milliseconds": 3930, "episode": 50, "trial": 10, "phase": "training", "completion_percentage": 23, "episode_status": "Off track"}, {"reward_score": 9, "metric_time": 182481, "start_time": 181149, "elapsed_time_in_milliseconds": 1332, "episode": 51, "trial": 11, "phase": "training", "completion_percentage": 5, "episode_status": "Off track"}, {"reward_score": 14, "metric_time": 185546, "start_time": 182548, "elapsed_time_in_milliseconds": 2998, "episode": 52, "trial": 12, "phase": "training", "completion_percentage": 15, "episode_status": "Off track"}, {"reward_score": 19, "metric_time": 188749, "start_time": 185616, "elapsed_time_in_milliseconds": 3133, "episode": 53, "trial": 13, "phase": "training", "completion_percentage": 18, "episode_status": "Off track"}, {"reward_score": 21, "metric_time": 191486, "start_time": 188814, "elapsed_time_in_milliseconds": 2672, "episode": 54, "trial": 14, "phase": "training", "completion_percentage": 14, "episode_status": "Off track"}, {"reward_score": 8, "metric_time": 192752, "start_time": 191544, "elapsed_time_in_milliseconds": 1208, "episode": 55, "trial": 15, "phase": "training", "completion_percentage": 3, "episode_status": "Off track"}, {"reward_score": 7, "metric_time": 194218, "start_time": 192819, "elapsed_time_in_milliseconds": 1399, "episode": 56, "trial": 16, "phase": "training", "completion_percentage": 6, "episode_status": "Off track"}, {"reward_score": 11, "metric_time": 196081, "start_time": 194282, "elapsed_time_in_milliseconds": 1799, "episode": 57, "trial": 17, "phase": "training", "completion_percentage": 8, "episode_status": "Off track"}, {"reward_score": 11, "metric_time": 197619, "start_time": 196144, "elapsed_time_in_milliseconds": 1475, "episode": 58, "trial": 18, "phase": "training", "completion_percentage": 5, "episode_status": "Off track"}, {"reward_score": 7, "metric_time": 198950, "start_time": 197675, "elapsed_time_in_milliseconds": 1275, "episode": 59, "trial": 19, "phase": "training", "completion_percentage": 4, "episode_status": "Off track"}, {"reward_score": 31, "metric_time": 202218, "start_time": 199006, "elapsed_time_in_milliseconds": 3212, "episode": 60, "trial": 20, "phase": "training", "completion_percentage": 18, "episode_status": "Off track"}, {"reward_score": 32, "metric_time": 207814, "start_time": 202352, "elapsed_time_in_milliseconds": 5462, "episode": 60, "trial": 20, "phase": "evaluation", "completion_percentage": 29, "episode_status": "Off track"}, {"reward_score": 39, "metric_time": 212416, "start_time": 207882, "elapsed_time_in_milliseconds": 4534, "episode": 60, "trial": 20, "phase": "evaluation", "completion_percentage": 24, "episode_status": "Off track"}, {"reward_score": 29, "metric_time": 216679, "start_time": 212484, "elapsed_time_in_milliseconds": 4195, "episode": 60, "trial": 20, "phase": "evaluation", "completion_percentage": 22, "episode_status": "Off track"}, {"reward_score": 51, "metric_time": 223885, "start_time": 216741, "elapsed_time_in_milliseconds": 7144, "episode": 60, "trial": 20, "phase": "evaluation", "completion_percentage": 35, "episode_status": "Off track"}, {"reward_score": 42, "metric_time": 229147, "start_time": 223950, "elapsed_time_in_milliseconds": 5197, "episode": 60, "trial": 20, "phase": "evaluation", "completion_percentage": 28, "episode_status": "Off track"}, {"reward_score": 14, "metric_time": 231687, "start_time": 229214, "elapsed_time_in_milliseconds": 2473, "episode": 61, "trial": 1, "phase": "training", "completion_percentage": 13, "episode_status": "Off track"}, {"reward_score": 33, "metric_time": 235084, "start_time": 231743, "elapsed_time_in_milliseconds": 3341, "episode": 62, "trial": 2, "phase": "training", "completion_percentage": 17, "episode_status": "Off track"}, {"reward_score": 25, "metric_time": 238483, "start_time": 235142, "elapsed_time_in_milliseconds": 3341, "episode": 63, "trial": 3, "phase": "training", "completion_percentage": 18, "episode_status": "Off track"}, {"reward_score": 21, "metric_time": 240616, "start_time": 238544, "elapsed_time_in_milliseconds": 2072, "episode": 64, "trial": 4, "phase": "training", "completion_percentage": 9, "episode_status": "Off track"}, {"reward_score": 13, "metric_time": 242219, "start_time": 240685, "elapsed_time_in_milliseconds": 1534, "episode": 65, "trial": 5, "phase": "training", "completion_percentage": 6, "episode_status": "Off track"}, {"reward_score": 12, "metric_time": 243890, "start_time": 242284, "elapsed_time_in_milliseconds": 1606, "episode": 66, "trial": 6, "phase": "training", "completion_percentage": 6, "episode_status": "Off track"}, {"reward_score": 17, "metric_time": 246086, "start_time": 243950, "elapsed_time_in_milliseconds": 2136, "episode": 67, "trial": 7, "phase": "training", "completion_percentage": 10, "episode_status": "Off track"}, {"reward_score": 27, "metric_time": 248687, "start_time": 246138, "elapsed_time_in_milliseconds": 2549, "episode": 68, "trial": 8, "phase": "training", "completion_percentage": 12, "episode_status": "Off track"}, {"reward_score": 14, "metric_time": 250417, "start_time": 248745, "elapsed_time_in_milliseconds": 1672, "episode": 69, "trial": 9, "phase": "training", "completion_percentage": 6, "episode_status": "Off track"}, {"reward_score": 9, "metric_time": 251886, "start_time": 250482, "elapsed_time_in_milliseconds": 1404, "episode": 70, "trial": 10, "phase": "training", "completion_percentage": 6, "episode_status": "Off track"}, {"reward_score": 29, "metric_time": 255214, "start_time": 251948, "elapsed_time_in_milliseconds": 3266, "episode": 71, "trial": 11, "phase": "training", "completion_percentage": 18, "episode_status": "Off track"}, {"reward_score": 13, "metric_time": 256880, "start_time": 255282, "elapsed_time_in_milliseconds": 1598, "episode": 72, "trial": 12, "phase": "training", "completion_percentage": 6, "episode_status": "Off track"}, {"reward_score": 28, "metric_time": 259550, "start_time": 256936, "elapsed_time_in_milliseconds": 2614, "episode": 73, "trial": 13, "phase": "training", "completion_percentage": 13, "episode_status": "Off track"}, {"reward_score": 10, "metric_time": 261081, "start_time": 259603, "elapsed_time_in_milliseconds": 1478, "episode": 74, "trial": 14, "phase": "training", "completion_percentage": 5, "episode_status": "Off track"}, {"reward_score": 11, "metric_time": 262816, "start_time": 261148, "elapsed_time_in_milliseconds": 1668, "episode": 75, "trial": 15, "phase": "training", "completion_percentage": 7, "episode_status": "Off track"}, {"reward_score": 39, "metric_time": 266883, "start_time": 262888, "elapsed_time_in_milliseconds": 3995, "episode": 76, "trial": 16, "phase": "training", "completion_percentage": 24, "episode_status": "Off track"}, {"reward_score": 28, "metric_time": 269538, "start_time": 266948, "elapsed_time_in_milliseconds": 2590, "episode": 77, "trial": 17, "phase": "training", "completion_percentage": 13, "episode_status": "Off track"}, {"reward_score": 18, "metric_time": 271678, "start_time": 269615, "elapsed_time_in_milliseconds": 2063, "episode": 78, "trial": 18, "phase": "training", "completion_percentage": 10, "episode_status": "Off track"}, {"reward_score": 10, "metric_time": 273286, "start_time": 271730, "elapsed_time_in_milliseconds": 1556, "episode": 79, "trial": 19, "phase": "training", "completion_percentage": 6, "episode_status": "Off track"}, {"reward_score": 56, "metric_time": 278752, "start_time": 273350, "elapsed_time_in_milliseconds": 5402, "episode": 80, "trial": 20, "phase": "training", "completion_percentage": 31, "episode_status": "Off track"}, {"reward_score": 52, "metric_time": 285749, "start_time": 278881, "elapsed_time_in_milliseconds": 6868, "episode": 80, "trial": 20, "phase": "evaluation", "completion_percentage": 38, "episode_status": "Off track"}, {"reward_score": 65, "metric_time": 292087, "start_time": 285816, "elapsed_time_in_milliseconds": 6271, "episode": 80, "trial": 20, "phase": "evaluation", "completion_percentage": 36, "episode_status": "Off track"}, {"reward_score": 94, "metric_time": 300095, "start_time": 292145, "elapsed_time_in_milliseconds": 7950, "episode": 80, "trial": 20, "phase": "evaluation", "completion_percentage": 47, "episode_status": "Off track"}, {"reward_score": 72, "metric_time": 308014, "start_time": 300148, "elapsed_time_in_milliseconds": 7866, "episode": 80, "trial": 20, "phase": "evaluation", "completion_percentage": 45, "episode_status": "Off track"}, {"reward_score": 97, "metric_time": 316015, "start_time": 308078, "elapsed_time_in_milliseconds": 7937, "episode": 80, "trial": 20, "phase": "evaluation", "completion_percentage": 45, "episode_status": "Off track"}, {"reward_score": 32, "metric_time": 320753, "start_time": 316086, "elapsed_time_in_milliseconds": 4667, "episode": 81, "trial": 1, "phase": "training", "completion_percentage": 27, "episode_status": "Off track"}, {"reward_score": 38, "metric_time": 324685, "start_time": 320813, "elapsed_time_in_milliseconds": 3872, "episode": 82, "trial": 2, "phase": "training", "completion_percentage": 22, "episode_status": "Off track"}, {"reward_score": 38, "metric_time": 328148, "start_time": 324703, "elapsed_time_in_milliseconds": 3445, "episode": 83, "trial": 3, "phase": "training", "completion_percentage": 17, "episode_status": "Off track"}, {"reward_score": 15, "metric_time": 330545, "start_time": 328210, "elapsed_time_in_milliseconds": 2335, "episode": 84, "trial": 4, "phase": "training", "completion_percentage": 11, "episode_status": "Off track"}, {"reward_score": 12, "metric_time": 332350, "start_time": 330608, "elapsed_time_in_milliseconds": 1742, "episode": 85, "trial": 5, "phase": "training", "completion_percentage": 7, "episode_status": "Off track"}, {"reward_score": 20, "metric_time": 334418, "start_time": 332416, "elapsed_time_in_milliseconds": 2002, "episode": 86, "trial": 6, "phase": "training", "completion_percentage": 8, "episode_status": "Off track"}, {"reward_score": 14, "metric_time": 336079, "start_time": 334481, "elapsed_time_in_milliseconds": 1598, "episode": 87, "trial": 7, "phase": "training", "completion_percentage": 6, "episode_status": "Off track"}, {"reward_score": 30, "metric_time": 339147, "start_time": 336143, "elapsed_time_in_milliseconds": 3004, "episode": 88, "trial": 8, "phase": "training", "completion_percentage": 17, "episode_status": "Off track"}, {"reward_score": 17, "metric_time": 341340, "start_time": 339214, "elapsed_time_in_milliseconds": 2126, "episode": 89, "trial": 9, "phase": "training", "completion_percentage": 10, "episode_status": "Off track"}, {"reward_score": 63, "metric_time": 346820, "start_time": 341414, "elapsed_time_in_milliseconds": 5406, "episode": 90, "trial": 10, "phase": "training", "completion_percentage": 31, "episode_status": "Off track"}, {"reward_score": 27, "metric_time": 349820, "start_time": 346880, "elapsed_time_in_milliseconds": 2940, "episode": 91, "trial": 11, "phase": "training", "completion_percentage": 16, "episode_status": "Off track"}, {"reward_score": 34, "metric_time": 353884, "start_time": 349884, "elapsed_time_in_milliseconds": 4000, "episode": 92, "trial": 12, "phase": "training", "completion_percentage": 23, "episode_status": "Off track"}, {"reward_score": 9, "metric_time": 355351, "start_time": 353953, "elapsed_time_in_milliseconds": 1398, "episode": 93, "trial": 13, "phase": "training", "completion_percentage": 6, "episode_status": "Off track"}, {"reward_score": 21, "metric_time": 357547, "start_time": 355406, "elapsed_time_in_milliseconds": 2141, "episode": 94, "trial": 14, "phase": "training", "completion_percentage": 10, "episode_status": "Off track"}, {"reward_score": 47, "metric_time": 362013, "start_time": 357571, "elapsed_time_in_milliseconds": 4442, "episode": 95, "trial": 15, "phase": "training", "completion_percentage": 24, "episode_status": "Off track"}, {"reward_score": 40, "metric_time": 365615, "start_time": 362071, "elapsed_time_in_milliseconds": 3544, "episode": 96, "trial": 16, "phase": "training", "completion_percentage": 17, "episode_status": "Off track"}, {"reward_score": 26, "metric_time": 368153, "start_time": 365680, "elapsed_time_in_milliseconds": 2473, "episode": 97, "trial": 17, "phase": "training", "completion_percentage": 11, "episode_status": "Off track"}, {"reward_score": 17, "metric_time": 370619, "start_time": 368211, "elapsed_time_in_milliseconds": 2408, "episode": 98, "trial": 18, "phase": "training", "completion_percentage": 13, "episode_status": "Off track"}, {"reward_score": 11, "metric_time": 373144, "start_time": 370663, "elapsed_time_in_milliseconds": 2481, "episode": 99, "trial": 19, "phase": "training", "completion_percentage": 13, "episode_status": "Off track"}, {"reward_score": 56, "metric_time": 378347, "start_time": 373215, "elapsed_time_in_milliseconds": 5132, "episode": 100, "trial": 20, "phase": "training", "completion_percentage": 29, "episode_status": "Off track"}, {"reward_score": 142, "metric_time": 390884, "start_time": 378483, "elapsed_time_in_milliseconds": 12401, "episode": 100, "trial": 20, "phase": "evaluation", "completion_percentage": 76, "episode_status": "Off track"}, {"reward_score": 142, "metric_time": 403211, "start_time": 390943, "elapsed_time_in_milliseconds": 12268, "episode": 100, "trial": 20, "phase": "evaluation", "completion_percentage": 75, "episode_status": "Off track"}, {"reward_score": 139, "metric_time": 418211, "start_time": 403279, "elapsed_time_in_milliseconds": 14932, "episode": 100, "trial": 20, "phase": "evaluation", "completion_percentage": 96, "episode_status": "Off track"}, {"reward_score": 49, "metric_time": 423882, "start_time": 418263, "elapsed_time_in_milliseconds": 5619, "episode": 100, "trial": 20, "phase": "evaluation", "completion_percentage": 30, "episode_status": "Off track"}, {"reward_score": 165, "metric_time": 439293, "start_time": 423936, "elapsed_time_in_milliseconds": 15357, "episode": 100, "trial": 20, "phase": "evaluation", "completion_percentage": 97, "episode_status": "Off track"}, {"reward_score": 46, "metric_time": 444350, "start_time": 439346, "elapsed_time_in_milliseconds": 5004, "episode": 101, "trial": 1, "phase": "training", "completion_percentage": 29, "episode_status": "Off track"}, {"reward_score": 26, "metric_time": 447215, "start_time": 444412, "elapsed_time_in_milliseconds": 2803, "episode": 102, "trial": 2, "phase": "training", "completion_percentage": 15, "episode_status": "Off track"}, {"reward_score": 30, "metric_time": 450283, "start_time": 447282, "elapsed_time_in_milliseconds": 3001, "episode": 103, "trial": 3, "phase": "training", "completion_percentage": 16, "episode_status": "Off track"}, {"reward_score": 20, "metric_time": 452348, "start_time": 450349, "elapsed_time_in_milliseconds": 1999, "episode": 104, "trial": 4, "phase": "training", "completion_percentage": 8, "episode_status": "Off track"}, {"reward_score": 15, "metric_time": 454216, "start_time": 452405, "elapsed_time_in_milliseconds": 1811, "episode": 105, "trial": 5, "phase": "training", "completion_percentage": 7, "episode_status": "Off track"}, {"reward_score": 7, "metric_time": 455482, "start_time": 454281, "elapsed_time_in_milliseconds": 1201, "episode": 106, "trial": 6, "phase": "training", "completion_percentage": 3, "episode_status": "Off track"}, {"reward_score": 15, "metric_time": 457420, "start_time": 455550, "elapsed_time_in_milliseconds": 1870, "episode": 107, "trial": 7, "phase": "training", "completion_percentage": 9, "episode_status": "Off track"}, {"reward_score": 67, "metric_time": 463347, "start_time": 457480, "elapsed_time_in_milliseconds": 5867, "episode": 108, "trial": 8, "phase": "training", "completion_percentage": 34, "episode_status": "Off track"}, {"reward_score": 31, "metric_time": 467274, "start_time": 463418, "elapsed_time_in_milliseconds": 3856, "episode": 109, "trial": 9, "phase": "training", "completion_percentage": 23, "episode_status": "Off track"}, {"reward_score": 61, "metric_time": 472352, "start_time": 467351, "elapsed_time_in_milliseconds": 5001, "episode": 110, "trial": 10, "phase": "training", "completion_percentage": 29, "episode_status": "Off track"}, {"reward_score": 22, "metric_time": 476018, "start_time": 472417, "elapsed_time_in_milliseconds": 3601, "episode": 111, "trial": 11, "phase": "training", "completion_percentage": 19, "episode_status": "Off track"}, {"reward_score": 35, "metric_time": 479216, "start_time": 476070, "elapsed_time_in_milliseconds": 3146, "episode": 112, "trial": 12, "phase": "training", "completion_percentage": 17, "episode_status": "Off track"}, {"reward_score": 25, "metric_time": 481818, "start_time": 479285, "elapsed_time_in_milliseconds": 2533, "episode": 113, "trial": 13, "phase": "training", "completion_percentage": 12, "episode_status": "Off track"}, {"reward_score": 16, "metric_time": 483619, "start_time": 481885, "elapsed_time_in_milliseconds": 1734, "episode": 114, "trial": 14, "phase": "training", "completion_percentage": 7, "episode_status": "Off track"}, {"reward_score": 21, "metric_time": 486151, "start_time": 483683, "elapsed_time_in_milliseconds": 2468, "episode": 115, "trial": 15, "phase": "training", "completion_percentage": 13, "episode_status": "Off track"}, {"reward_score": 17, "metric_time": 488287, "start_time": 486216, "elapsed_time_in_milliseconds": 2071, "episode": 116, "trial": 16, "phase": "training", "completion_percentage": 11, "episode_status": "Off track"}, {"reward_score": 31, "metric_time": 491215, "start_time": 488305, "elapsed_time_in_milliseconds": 2910, "episode": 117, "trial": 17, "phase": "training", "completion_percentage": 15, "episode_status": "Off track"}, {"reward_score": 72, "metric_time": 498415, "start_time": 491280, "elapsed_time_in_milliseconds": 7135, "episode": 118, "trial": 18, "phase": "training", "completion_percentage": 41, "episode_status": "Off track"}, {"reward_score": 11, "metric_time": 500489, "start_time": 498480, "elapsed_time_in_milliseconds": 2009, "episode": 119, "trial": 19, "phase": "training", "completion_percentage": 10, "episode_status": "Off track"}, {"reward_score": 67, "metric_time": 505950, "start_time": 500550, "elapsed_time_in_milliseconds": 5400, "episode": 120, "trial": 20, "phase": "training", "completion_percentage": 31, "episode_status": "Off track"}, {"reward_score": 193, "metric_time": 521617, "start_time": 506080, "elapsed_time_in_milliseconds": 15537, "episode": 120, "trial": 20, "phase": "evaluation", "completion_percentage": 100, "episode_status": "Lap complete"}, {"reward_score": 66, "metric_time": 527681, "start_time": 521676, "elapsed_time_in_milliseconds": 6005, "episode": 120, "trial": 20, "phase": "evaluation", "completion_percentage": 34, "episode_status": "Off track"}, {"reward_score": 75, "metric_time": 534013, "start_time": 527743, "elapsed_time_in_milliseconds": 6270, "episode": 120, "trial": 20, "phase": "evaluation", "completion_percentage": 38, "episode_status": "Off track"}, {"reward_score": 66, "metric_time": 539616, "start_time": 534054, "elapsed_time_in_milliseconds": 5562, "episode": 120, "trial": 20, "phase": "evaluation", "completion_percentage": 32, "episode_status": "Off track"}, {"reward_score": 64, "metric_time": 545421, "start_time": 539684, "elapsed_time_in_milliseconds": 5737, "episode": 120, "trial": 20, "phase": "evaluation", "completion_percentage": 33, "episode_status": "Off track"}, {"reward_score": 15, "metric_time": 547351, "start_time": 545480, "elapsed_time_in_milliseconds": 1871, "episode": 121, "trial": 1, "phase": "training", "completion_percentage": 9, "episode_status": "Off track"}, {"reward_score": 36, "metric_time": 551020, "start_time": 547415, "elapsed_time_in_milliseconds": 3605, "episode": 122, "trial": 2, "phase": "training", "completion_percentage": 18, "episode_status": "Off track"}, {"reward_score": 18, "metric_time": 554216, "start_time": 551050, "elapsed_time_in_milliseconds": 3166, "episode": 123, "trial": 3, "phase": "training", "completion_percentage": 17, "episode_status": "Off track"}, {"reward_score": 16, "metric_time": 556884, "start_time": 554283, "elapsed_time_in_milliseconds": 2601, "episode": 124, "trial": 4, "phase": "training", "completion_percentage": 14, "episode_status": "Off track"}, {"reward_score": 60, "metric_time": 562216, "start_time": 556949, "elapsed_time_in_milliseconds": 5267, "episode": 125, "trial": 5, "phase": "training", "completion_percentage": 29, "episode_status": "Off track"}, {"reward_score": 18, "metric_time": 564549, "start_time": 562282, "elapsed_time_in_milliseconds": 2267, "episode": 126, "trial": 6, "phase": "training", "completion_percentage": 10, "episode_status": "Off track"}, {"reward_score": 64, "metric_time": 571147, "start_time": 564614, "elapsed_time_in_milliseconds": 6533, "episode": 127, "trial": 7, "phase": "training", "completion_percentage": 41, "episode_status": "Off track"}, {"reward_score": 17, "metric_time": 574015, "start_time": 571218, "elapsed_time_in_milliseconds": 2797, "episode": 128, "trial": 8, "phase": "training", "completion_percentage": 16, "episode_status": "Off track"}, {"reward_score": 36, "metric_time": 579615, "start_time": 574084, "elapsed_time_in_milliseconds": 5531, "episode": 129, "trial": 9, "phase": "training", "completion_percentage": 33, "episode_status": "Off track"}, {"reward_score": 31, "metric_time": 582414, "start_time": 579683, "elapsed_time_in_milliseconds": 2731, "episode": 130, "trial": 10, "phase": "training", "completion_percentage": 13, "episode_status": "Off track"}, {"reward_score": 44, "metric_time": 586415, "start_time": 582470, "elapsed_time_in_milliseconds": 3945, "episode": 131, "trial": 11, "phase": "training", "completion_percentage": 22, "episode_status": "Off track"}, {"reward_score": 36, "metric_time": 589814, "start_time": 586483, "elapsed_time_in_milliseconds": 3331, "episode": 132, "trial": 12, "phase": "training", "completion_percentage": 17, "episode_status": "Off track"}, {"reward_score": 30, "metric_time": 592817, "start_time": 589880, "elapsed_time_in_milliseconds": 2937, "episode": 133, "trial": 13, "phase": "training", "completion_percentage": 15, "episode_status": "Off track"}, {"reward_score": 8, "metric_time": 594203, "start_time": 592881, "elapsed_time_in_milliseconds": 1322, "episode": 134, "trial": 14, "phase": "training", "completion_percentage": 5, "episode_status": "Off track"}, {"reward_score": 37, "metric_time": 598347, "start_time": 594282, "elapsed_time_in_milliseconds": 4065, "episode": 135, "trial": 15, "phase": "training", "completion_percentage": 23, "episode_status": "Off track"}, {"reward_score": 43, "metric_time": 601871, "start_time": 598412, "elapsed_time_in_milliseconds": 3459, "episode": 136, "trial": 16, "phase": "training", "completion_percentage": 18, "episode_status": "Off track"}, {"reward_score": 26, "metric_time": 604484, "start_time": 601909, "elapsed_time_in_milliseconds": 2575, "episode": 137, "trial": 17, "phase": "training", "completion_percentage": 12, "episode_status": "Off track"}, {"reward_score": 20, "metric_time": 606755, "start_time": 604544, "elapsed_time_in_milliseconds": 2211, "episode": 138, "trial": 18, "phase": "training", "completion_percentage": 10, "episode_status": "Off track"}, {"reward_score": 72, "metric_time": 613087, "start_time": 606814, "elapsed_time_in_milliseconds": 6273, "episode": 139, "trial": 19, "phase": "training", "completion_percentage": 36, "episode_status": "Off track"}, {"reward_score": 49, "metric_time": 618417, "start_time": 613149, "elapsed_time_in_milliseconds": 5268, "episode": 140, "trial": 20, "phase": "training", "completion_percentage": 30, "episode_status": "Off track"}, {"reward_score": 59, "metric_time": 624414, "start_time": 618543, "elapsed_time_in_milliseconds": 5871, "episode": 140, "trial": 20, "phase": "evaluation", "completion_percentage": 33, "episode_status": "Off track"}, {"reward_score": 183, "metric_time": 639487, "start_time": 624454, "elapsed_time_in_milliseconds": 15033, "episode": 140, "trial": 20, "phase": "evaluation", "completion_percentage": 100, "episode_status": "Lap complete"}, {"reward_score": 160, "metric_time": 654213, "start_time": 639545, "elapsed_time_in_milliseconds": 14668, "episode": 140, "trial": 20, "phase": "evaluation", "completion_percentage": 100, "episode_status": "Lap complete"}, {"reward_score": 156, "metric_time": 668948, "start_time": 654285, "elapsed_time_in_milliseconds": 14663, "episode": 140, "trial": 20, "phase": "evaluation", "completion_percentage": 100, "episode_status": "Lap complete"}, {"reward_score": 63, "metric_time": 674885, "start_time": 669014, "elapsed_time_in_milliseconds": 5871, "episode": 140, "trial": 20, "phase": "evaluation", "completion_percentage": 34, "episode_status": "Off track"}, {"reward_score": 34, "metric_time": 678020, "start_time": 674947, "elapsed_time_in_milliseconds": 3073, "episode": 141, "trial": 1, "phase": "training", "completion_percentage": 17, "episode_status": "Off track"}, {"reward_score": 34, "metric_time": 681481, "start_time": 678085, "elapsed_time_in_milliseconds": 3396, "episode": 142, "trial": 2, "phase": "training", "completion_percentage": 18, "episode_status": "Off track"}, {"reward_score": 73, "metric_time": 687690, "start_time": 681517, "elapsed_time_in_milliseconds": 6173, "episode": 143, "trial": 3, "phase": "training", "completion_percentage": 37, "episode_status": "Off track"}, {"reward_score": 12, "metric_time": 689281, "start_time": 687748, "elapsed_time_in_milliseconds": 1533, "episode": 144, "trial": 4, "phase": "training", "completion_percentage": 6, "episode_status": "Off track"}, {"reward_score": 16, "metric_time": 692019, "start_time": 689346, "elapsed_time_in_milliseconds": 2673, "episode": 145, "trial": 5, "phase": "training", "completion_percentage": 14, "episode_status": "Off track"}, {"reward_score": 15, "metric_time": 693818, "start_time": 692081, "elapsed_time_in_milliseconds": 1737, "episode": 146, "trial": 6, "phase": "training", "completion_percentage": 7, "episode_status": "Off track"}, {"reward_score": 79, "metric_time": 701215, "start_time": 693880, "elapsed_time_in_milliseconds": 7335, "episode": 147, "trial": 7, "phase": "training", "completion_percentage": 43, "episode_status": "Off track"}, {"reward_score": 10, "metric_time": 702751, "start_time": 701278, "elapsed_time_in_milliseconds": 1473, "episode": 148, "trial": 8, "phase": "training", "completion_percentage": 6, "episode_status": "Off track"}, {"reward_score": 126, "metric_time": 715817, "start_time": 702786, "elapsed_time_in_milliseconds": 13031, "episode": 149, "trial": 9, "phase": "training", "completion_percentage": 80, "episode_status": "Off track"}, {"reward_score": 30, "metric_time": 719155, "start_time": 715881, "elapsed_time_in_milliseconds": 3274, "episode": 150, "trial": 10, "phase": "training", "completion_percentage": 18, "episode_status": "Off track"}, {"reward_score": 11, "metric_time": 721014, "start_time": 719213, "elapsed_time_in_milliseconds": 1801, "episode": 151, "trial": 11, "phase": "training", "completion_percentage": 8, "episode_status": "Off track"}, {"reward_score": 118, "metric_time": 732953, "start_time": 721081, "elapsed_time_in_milliseconds": 11872, "episode": 152, "trial": 12, "phase": "training", "completion_percentage": 78, "episode_status": "Off track"}, {"reward_score": 33, "metric_time": 736353, "start_time": 733012, "elapsed_time_in_milliseconds": 3341, "episode": 153, "trial": 13, "phase": "training", "completion_percentage": 18, "episode_status": "Off track"}, {"reward_score": 82, "metric_time": 745684, "start_time": 736414, "elapsed_time_in_milliseconds": 9270, "episode": 154, "trial": 14, "phase": "training", "completion_percentage": 56, "episode_status": "Off track"}, {"reward_score": 11, "metric_time": 747214, "start_time": 745747, "elapsed_time_in_milliseconds": 1467, "episode": 155, "trial": 15, "phase": "training", "completion_percentage": 6, "episode_status": "Off track"}, {"reward_score": 39, "metric_time": 750610, "start_time": 747285, "elapsed_time_in_milliseconds": 3325, "episode": 156, "trial": 16, "phase": "training", "completion_percentage": 16, "episode_status": "Off track"}, {"reward_score": 32, "metric_time": 753493, "start_time": 750682, "elapsed_time_in_milliseconds": 2811, "episode": 157, "trial": 17, "phase": "training", "completion_percentage": 14, "episode_status": "Off track"}, {"reward_score": 16, "metric_time": 755348, "start_time": 753549, "elapsed_time_in_milliseconds": 1799, "episode": 158, "trial": 18, "phase": "training", "completion_percentage": 8, "episode_status": "Off track"}, {"reward_score": 93, "metric_time": 763283, "start_time": 755414, "elapsed_time_in_milliseconds": 7869, "episode": 159, "trial": 19, "phase": "training", "completion_percentage": 47, "episode_status": "Off track"}, {"reward_score": 75, "metric_time": 769413, "start_time": 763348, "elapsed_time_in_milliseconds": 6065, "episode": 160, "trial": 20, "phase": "training", "completion_percentage": 35, "episode_status": "Off track"}, {"reward_score": 56, "metric_time": 775411, "start_time": 769530, "elapsed_time_in_milliseconds": 5881, "episode": 160, "trial": 20, "phase": "evaluation", "completion_percentage": 35, "episode_status": "Off track"}, {"reward_score": 167, "metric_time": 790016, "start_time": 775480, "elapsed_time_in_milliseconds": 14536, "episode": 160, "trial": 20, "phase": "evaluation", "completion_percentage": 100, "episode_status": "Lap complete"}, {"reward_score": 65, "metric_time": 795820, "start_time": 790084, "elapsed_time_in_milliseconds": 5736, "episode": 160, "trial": 20, "phase": "evaluation", "completion_percentage": 34, "episode_status": "Off track"}, {"reward_score": 150, "metric_time": 810085, "start_time": 795871, "elapsed_time_in_milliseconds": 14214, "episode": 160, "trial": 20, "phase": "evaluation", "completion_percentage": 100, "episode_status": "Lap complete"}, {"reward_score": 148, "metric_time": 824481, "start_time": 810137, "elapsed_time_in_milliseconds": 14344, "episode": 160, "trial": 20, "phase": "evaluation", "completion_percentage": 100, "episode_status": "Lap complete"}, {"reward_score": 53, "metric_time": 829670, "start_time": 824552, "elapsed_time_in_milliseconds": 5118, "episode": 161, "trial": 1, "phase": "training", "completion_percentage": 30, "episode_status": "Off track"}, {"reward_score": 42, "metric_time": 833418, "start_time": 829744, "elapsed_time_in_milliseconds": 3674, "episode": 162, "trial": 2, "phase": "training", "completion_percentage": 20, "episode_status": "Off track"}, {"reward_score": 108, "metric_time": 843409, "start_time": 833483, "elapsed_time_in_milliseconds": 9926, "episode": 163, "trial": 3, "phase": "training", "completion_percentage": 60, "episode_status": "Off track"}, {"reward_score": 61, "metric_time": 849017, "start_time": 843490, "elapsed_time_in_milliseconds": 5527, "episode": 164, "trial": 4, "phase": "training", "completion_percentage": 33, "episode_status": "Off track"}, {"reward_score": 21, "metric_time": 851484, "start_time": 849081, "elapsed_time_in_milliseconds": 2403, "episode": 165, "trial": 5, "phase": "training", "completion_percentage": 12, "episode_status": "Off track"}, {"reward_score": 37, "metric_time": 855222, "start_time": 851547, "elapsed_time_in_milliseconds": 3675, "episode": 166, "trial": 6, "phase": "training", "completion_percentage": 20, "episode_status": "Off track"}, {"reward_score": 23, "metric_time": 858949, "start_time": 855283, "elapsed_time_in_milliseconds": 3666, "episode": 167, "trial": 7, "phase": "training", "completion_percentage": 21, "episode_status": "Off track"}, {"reward_score": 67, "metric_time": 865815, "start_time": 859013, "elapsed_time_in_milliseconds": 6802, "episode": 168, "trial": 8, "phase": "training", "completion_percentage": 42, "episode_status": "Off track"}, {"reward_score": 11, "metric_time": 867350, "start_time": 865878, "elapsed_time_in_milliseconds": 1472, "episode": 169, "trial": 9, "phase": "training", "completion_percentage": 5, "episode_status": "Off track"}, {"reward_score": 92, "metric_time": 875743, "start_time": 867415, "elapsed_time_in_milliseconds": 8328, "episode": 170, "trial": 10, "phase": "training", "completion_percentage": 50, "episode_status": "Off track"}, {"reward_score": 43, "metric_time": 880283, "start_time": 875809, "elapsed_time_in_milliseconds": 4474, "episode": 171, "trial": 11, "phase": "training", "completion_percentage": 25, "episode_status": "Off track"}, {"reward_score": 60, "metric_time": 885687, "start_time": 880350, "elapsed_time_in_milliseconds": 5337, "episode": 172, "trial": 12, "phase": "training", "completion_percentage": 33, "episode_status": "Off track"}, {"reward_score": 124, "metric_time": 897081, "start_time": 885747, "elapsed_time_in_milliseconds": 11334, "episode": 173, "trial": 13, "phase": "training", "completion_percentage": 72, "episode_status": "Off track"}, {"reward_score": 14, "metric_time": 898751, "start_time": 897144, "elapsed_time_in_milliseconds": 1607, "episode": 174, "trial": 14, "phase": "training", "completion_percentage": 6, "episode_status": "Off track"}, {"reward_score": 122, "metric_time": 908751, "start_time": 898812, "elapsed_time_in_milliseconds": 9939, "episode": 175, "trial": 15, "phase": "training", "completion_percentage": 62, "episode_status": "Off track"}, {"reward_score": 38, "metric_time": 912483, "start_time": 908811, "elapsed_time_in_milliseconds": 3672, "episode": 176, "trial": 16, "phase": "training", "completion_percentage": 20, "episode_status": "Off track"}, {"reward_score": 84, "metric_time": 919220, "start_time": 912548, "elapsed_time_in_milliseconds": 6672, "episode": 177, "trial": 17, "phase": "training", "completion_percentage": 39, "episode_status": "Off track"}, {"reward_score": 16, "metric_time": 921308, "start_time": 919281, "elapsed_time_in_milliseconds": 2027, "episode": 178, "trial": 18, "phase": "training", "completion_percentage": 10, "episode_status": "Off track"}, {"reward_score": 72, "metric_time": 927950, "start_time": 921382, "elapsed_time_in_milliseconds": 6568, "episode": 179, "trial": 19, "phase": "training", "completion_percentage": 39, "episode_status": "Off track"}, {"reward_score": 68, "metric_time": 933747, "start_time": 928012, "elapsed_time_in_milliseconds": 5735, "episode": 180, "trial": 20, "phase": "training", "completion_percentage": 33, "episode_status": "Off track"}, {"reward_score": 151, "metric_time": 948401, "start_time": 933867, "elapsed_time_in_milliseconds": 14534, "episode": 180, "trial": 20, "phase": "evaluation", "completion_percentage": 100, "episode_status": "Lap complete"}, {"reward_score": 140, "metric_time": 962489, "start_time": 948485, "elapsed_time_in_milliseconds": 14004, "episode": 180, "trial": 20, "phase": "evaluation", "completion_percentage": 100, "episode_status": "Lap complete"}, {"reward_score": 166, "metric_time": 977346, "start_time": 962550, "elapsed_time_in_milliseconds": 14796, "episode": 180, "trial": 20, "phase": "evaluation", "completion_percentage": 100, "episode_status": "Lap complete"}, {"reward_score": 137, "metric_time": 991955, "start_time": 977412, "elapsed_time_in_milliseconds": 14543, "episode": 180, "trial": 20, "phase": "evaluation", "completion_percentage": 100, "episode_status": "Lap complete"}, {"reward_score": 165, "metric_time": 1006884, "start_time": 992015, "elapsed_time_in_milliseconds": 14869, "episode": 180, "trial": 20, "phase": "evaluation", "completion_percentage": 100, "episode_status": "Lap complete"}, {"reward_score": 49, "metric_time": 1011214, "start_time": 1006944, "elapsed_time_in_milliseconds": 4270, "episode": 181, "trial": 1, "phase": "training", "completion_percentage": 24, "episode_status": "Off track"}, {"reward_score": 104, "metric_time": 1021014, "start_time": 1011285, "elapsed_time_in_milliseconds": 9729, "episode": 182, "trial": 2, "phase": "training", "completion_percentage": 65, "episode_status": "Off track"}, {"reward_score": 152, "metric_time": 1035947, "start_time": 1021081, "elapsed_time_in_milliseconds": 14866, "episode": 183, "trial": 3, "phase": "training", "completion_percentage": 100, "episode_status": "Lap complete"}, {"reward_score": 20, "metric_time": 1038419, "start_time": 1036014, "elapsed_time_in_milliseconds": 2405, "episode": 184, "trial": 4, "phase": "training", "completion_percentage": 12, "episode_status": "Off track"}, {"reward_score": 44, "metric_time": 1043352, "start_time": 1038475, "elapsed_time_in_milliseconds": 4877, "episode": 185, "trial": 5, "phase": "training", "completion_percentage": 29, "episode_status": "Off track"}, {"reward_score": 11, "metric_time": 1044753, "start_time": 1043413, "elapsed_time_in_milliseconds": 1340, "episode": 186, "trial": 6, "phase": "training", "completion_percentage": 4, "episode_status": "Off track"}, {"reward_score": 41, "metric_time": 1048752, "start_time": 1044814, "elapsed_time_in_milliseconds": 3938, "episode": 187, "trial": 7, "phase": "training", "completion_percentage": 22, "episode_status": "Off track"}, {"reward_score": 88, "metric_time": 1057818, "start_time": 1048814, "elapsed_time_in_milliseconds": 9004, "episode": 188, "trial": 8, "phase": "training", "completion_percentage": 57, "episode_status": "Off track"}, {"reward_score": 13, "metric_time": 1060081, "start_time": 1057883, "elapsed_time_in_milliseconds": 2198, "episode": 189, "trial": 9, "phase": "training", "completion_percentage": 11, "episode_status": "Off track"}, {"reward_score": 99, "metric_time": 1068548, "start_time": 1060147, "elapsed_time_in_milliseconds": 8401, "episode": 190, "trial": 10, "phase": "training", "completion_percentage": 51, "episode_status": "Off track"}, {"reward_score": 81, "metric_time": 1075882, "start_time": 1068608, "elapsed_time_in_milliseconds": 7274, "episode": 191, "trial": 11, "phase": "training", "completion_percentage": 45, "episode_status": "Off track"}, {"reward_score": 31, "metric_time": 1079950, "start_time": 1075930, "elapsed_time_in_milliseconds": 4020, "episode": 192, "trial": 12, "phase": "training", "completion_percentage": 25, "episode_status": "Off track"}, {"reward_score": 39, "metric_time": 1084447, "start_time": 1080016, "elapsed_time_in_milliseconds": 4431, "episode": 193, "trial": 13, "phase": "training", "completion_percentage": 26, "episode_status": "Off track"}, {"reward_score": 19, "metric_time": 1086483, "start_time": 1084550, "elapsed_time_in_milliseconds": 1933, "episode": 194, "trial": 14, "phase": "training", "completion_percentage": 8, "episode_status": "Off track"}, {"reward_score": 41, "metric_time": 1090482, "start_time": 1086548, "elapsed_time_in_milliseconds": 3934, "episode": 195, "trial": 15, "phase": "training", "completion_percentage": 20, "episode_status": "Off track"}, {"reward_score": 15, "metric_time": 1092484, "start_time": 1090530, "elapsed_time_in_milliseconds": 1954, "episode": 196, "trial": 16, "phase": "training", "completion_percentage": 10, "episode_status": "Off track"}, {"reward_score": 103, "metric_time": 1101285, "start_time": 1092547, "elapsed_time_in_milliseconds": 8738, "episode": 197, "trial": 17, "phase": "training", "completion_percentage": 55, "episode_status": "Off track"}, {"reward_score": 60, "metric_time": 1106758, "start_time": 1101349, "elapsed_time_in_milliseconds": 5409, "episode": 198, "trial": 18, "phase": "training", "completion_percentage": 32, "episode_status": "Off track"}, {"reward_score": 74, "metric_time": 1113750, "start_time": 1106793, "elapsed_time_in_milliseconds": 6957, "episode": 199, "trial": 19, "phase": "training", "completion_percentage": 42, "episode_status": "Off track"}, {"reward_score": 163, "metric_time": 1126556, "start_time": 1113803, "elapsed_time_in_milliseconds": 12753, "episode": 200, "trial": 20, "phase": "training", "completion_percentage": 80, "episode_status": "Off track"}, {"reward_score": 160, "metric_time": 1141131, "start_time": 1126687, "elapsed_time_in_milliseconds": 14444, "episode": 200, "trial": 20, "phase": "evaluation", "completion_percentage": 100, "episode_status": "Lap complete"}, {"reward_score": 109, "metric_time": 1152663, "start_time": 1141211, "elapsed_time_in_milliseconds": 11452, "episode": 200, "trial": 20, "phase": "evaluation", "completion_percentage": 78, "episode_status": "Off track"}, {"reward_score": 146, "metric_time": 1167151, "start_time": 1152745, "elapsed_time_in_milliseconds": 14406, "episode": 200, "trial": 20, "phase": "evaluation", "completion_percentage": 100, "episode_status": "Lap complete"}, {"reward_score": 155, "metric_time": 1181990, "start_time": 1167212, "elapsed_time_in_milliseconds": 14778, "episode": 200, "trial": 20, "phase": "evaluation", "completion_percentage": 100, "episode_status": "Lap complete"}, {"reward_score": 152, "metric_time": 1196548, "start_time": 1182060, "elapsed_time_in_milliseconds": 14488, "episode": 200, "trial": 20, "phase": "evaluation", "completion_percentage": 100, "episode_status": "Lap complete"}, {"reward_score": 72, "metric_time": 1202753, "start_time": 1196618, "elapsed_time_in_milliseconds": 6135, "episode": 201, "trial": 1, "phase": "training", "completion_percentage": 36, "episode_status": "Off track"}, {"reward_score": 12, "metric_time": 1204618, "start_time": 1202816, "elapsed_time_in_milliseconds": 1802, "episode": 202, "trial": 2, "phase": "training", "completion_percentage": 9, "episode_status": "Off track"}, {"reward_score": 30, "metric_time": 1207542, "start_time": 1204686, "elapsed_time_in_milliseconds": 2856, "episode": 203, "trial": 3, "phase": "training", "completion_percentage": 14, "episode_status": "Off track"}, {"reward_score": 92, "metric_time": 1215550, "start_time": 1207613, "elapsed_time_in_milliseconds": 7937, "episode": 204, "trial": 4, "phase": "training", "completion_percentage": 49, "episode_status": "Off track"}, {"reward_score": 16, "metric_time": 1217878, "start_time": 1215611, "elapsed_time_in_milliseconds": 2267, "episode": 205, "trial": 5, "phase": "training", "completion_percentage": 10, "episode_status": "Off track"}, {"reward_score": 48, "metric_time": 1222687, "start_time": 1217950, "elapsed_time_in_milliseconds": 4737, "episode": 206, "trial": 6, "phase": "training", "completion_percentage": 28, "episode_status": "Off track"}, {"reward_score": 173, "metric_time": 1238021, "start_time": 1222744, "elapsed_time_in_milliseconds": 15277, "episode": 207, "trial": 7, "phase": "training", "completion_percentage": 100, "episode_status": "Lap complete"}, {"reward_score": 57, "metric_time": 1244278, "start_time": 1238082, "elapsed_time_in_milliseconds": 6196, "episode": 208, "trial": 8, "phase": "training", "completion_percentage": 37, "episode_status": "Off track"}, {"reward_score": 23, "metric_time": 1246614, "start_time": 1244350, "elapsed_time_in_milliseconds": 2264, "episode": 209, "trial": 9, "phase": "training", "completion_percentage": 11, "episode_status": "Off track"}, {"reward_score": 29, "metric_time": 1249551, "start_time": 1246685, "elapsed_time_in_milliseconds": 2866, "episode": 210, "trial": 10, "phase": "training", "completion_percentage": 15, "episode_status": "Off track"}, {"reward_score": 128, "metric_time": 1260152, "start_time": 1249616, "elapsed_time_in_milliseconds": 10536, "episode": 211, "trial": 11, "phase": "training", "completion_percentage": 66, "episode_status": "Off track"}, {"reward_score": 173, "metric_time": 1274879, "start_time": 1260214, "elapsed_time_in_milliseconds": 14665, "episode": 212, "trial": 12, "phase": "training", "completion_percentage": 100, "episode_status": "Lap complete"}, {"reward_score": 135, "metric_time": 1286344, "start_time": 1274949, "elapsed_time_in_milliseconds": 11395, "episode": 213, "trial": 13, "phase": "training", "completion_percentage": 72, "episode_status": "Off track"}, {"reward_score": 111, "metric_time": 1296615, "start_time": 1286417, "elapsed_time_in_milliseconds": 10198, "episode": 214, "trial": 14, "phase": "training", "completion_percentage": 63, "episode_status": "Off track"}, {"reward_score": 179, "metric_time": 1311747, "start_time": 1296683, "elapsed_time_in_milliseconds": 15064, "episode": 215, "trial": 15, "phase": "training", "completion_percentage": 100, "episode_status": "Lap complete"}, {"reward_score": 8, "metric_time": 1313150, "start_time": 1311818, "elapsed_time_in_milliseconds": 1332, "episode": 216, "trial": 16, "phase": "training", "completion_percentage": 6, "episode_status": "Off track"}, {"reward_score": 141, "metric_time": 1324349, "start_time": 1313216, "elapsed_time_in_milliseconds": 11133, "episode": 217, "trial": 17, "phase": "training", "completion_percentage": 71, "episode_status": "Off track"}, {"reward_score": 197, "metric_time": 1339883, "start_time": 1324412, "elapsed_time_in_milliseconds": 15471, "episode": 218, "trial": 18, "phase": "training", "completion_percentage": 100, "episode_status": "Lap complete"}, {"reward_score": 79, "metric_time": 1346811, "start_time": 1339948, "elapsed_time_in_milliseconds": 6863, "episode": 219, "trial": 19, "phase": "training", "completion_percentage": 41, "episode_status": "Off track"}, {"reward_score": 102, "metric_time": 1355950, "start_time": 1346876, "elapsed_time_in_milliseconds": 9074, "episode": 220, "trial": 20, "phase": "training", "completion_percentage": 57, "episode_status": "Off track"}, {"reward_score": 174, "metric_time": 1371150, "start_time": 1356077, "elapsed_time_in_milliseconds": 15073, "episode": 220, "trial": 20, "phase": "evaluation", "completion_percentage": 100, "episode_status": "Lap complete"}, {"reward_score": 162, "metric_time": 1386079, "start_time": 1371217, "elapsed_time_in_milliseconds": 14862, "episode": 220, "trial": 20, "phase": "evaluation", "completion_percentage": 100, "episode_status": "Lap complete"}, {"reward_score": 166, "metric_time": 1400795, "start_time": 1386135, "elapsed_time_in_milliseconds": 14660, "episode": 220, "trial": 20, "phase": "evaluation", "completion_percentage": 100, "episode_status": "Lap complete"}, {"reward_score": 172, "metric_time": 1416085, "start_time": 1400879, "elapsed_time_in_milliseconds": 15206, "episode": 220, "trial": 20, "phase": "evaluation", "completion_percentage": 100, "episode_status": "Lap complete"}, {"reward_score": 161, "metric_time": 1431347, "start_time": 1416140, "elapsed_time_in_milliseconds": 15207, "episode": 220, "trial": 20, "phase": "evaluation", "completion_percentage": 100, "episode_status": "Lap complete"}, {"reward_score": 194, "metric_time": 1446684, "start_time": 1431415, "elapsed_time_in_milliseconds": 15269, "episode": 221, "trial": 1, "phase": "training", "completion_percentage": 100, "episode_status": "Lap complete"}, {"reward_score": 37, "metric_time": 1450214, "start_time": 1446743, "elapsed_time_in_milliseconds": 3471, "episode": 222, "trial": 2, "phase": "training", "completion_percentage": 19, "episode_status": "Off track"}, {"reward_score": 39, "metric_time": 1453887, "start_time": 1450281, "elapsed_time_in_milliseconds": 3606, "episode": 223, "trial": 3, "phase": "training", "completion_percentage": 18, "episode_status": "Off track"}, {"reward_score": 149, "metric_time": 1466218, "start_time": 1453949, "elapsed_time_in_milliseconds": 12269, "episode": 224, "trial": 4, "phase": "training", "completion_percentage": 76, "episode_status": "Off track"}, {"reward_score": 171, "metric_time": 1481489, "start_time": 1466281, "elapsed_time_in_milliseconds": 15208, "episode": 225, "trial": 5, "phase": "training", "completion_percentage": 100, "episode_status": "Lap complete"}, {"reward_score": 160, "metric_time": 1495479, "start_time": 1481548, "elapsed_time_in_milliseconds": 13931, "episode": 226, "trial": 6, "phase": "training", "completion_percentage": 88, "episode_status": "Off track"}, {"reward_score": 45, "metric_time": 1501083, "start_time": 1495544, "elapsed_time_in_milliseconds": 5539, "episode": 227, "trial": 7, "phase": "training", "completion_percentage": 36, "episode_status": "Off track"}, {"reward_score": 10, "metric_time": 1502818, "start_time": 1501117, "elapsed_time_in_milliseconds": 1701, "episode": 228, "trial": 8, "phase": "training", "completion_percentage": 8, "episode_status": "Off track"}, {"reward_score": 155, "metric_time": 1516951, "start_time": 1502879, "elapsed_time_in_milliseconds": 14072, "episode": 229, "trial": 9, "phase": "training", "completion_percentage": 90, "episode_status": "Off track"}, {"reward_score": 54, "metric_time": 1521751, "start_time": 1517016, "elapsed_time_in_milliseconds": 4735, "episode": 230, "trial": 10, "phase": "training", "completion_percentage": 27, "episode_status": "Off track"}, {"reward_score": 41, "metric_time": 1526086, "start_time": 1521814, "elapsed_time_in_milliseconds": 4272, "episode": 231, "trial": 11, "phase": "training", "completion_percentage": 23, "episode_status": "Off track"}], "version": 2.0, "best_model_metric": "progress"}